solar_radiation/__init__.py
solar_radiation/core/__init__.py
solar_radiation/core/extraterrestrial_radiation.py
solar_radiation/core/solar_geometry.py
solar_radiation/core/utils.py
solar_radiation/solar_radiation.py
solar_radiation-0.1.2.dist-info/LICENSE
solar_radiation-0.1.2.dist-info/METADATA
solar_radiation-0.1.2.dist-info/WHEEL
solar_radiation-0.1.2.dist-info/RECORD
