Metadata-Version: 2.3
Name: solar-radiation
Version: 0.1.2
Summary: solar-radiation is a high-resolution solar irradiance calculator that computes extraterrestrial solar radiation flux at user-defined time intervals.
License: MIT
Author: Hiksang
Requires-Python: >=3.11
Classifier: License :: OSI Approved :: MIT License
Classifier: Programming Language :: Python :: 3
Classifier: Programming Language :: Python :: 3.11
Classifier: Programming Language :: Python :: 3.12
Classifier: Programming Language :: Python :: 3.13
Requires-Dist: pandas (>=2.2.3,<3.0.0)
